vorlagellm/__init__.py
vorlagellm/agreements.py
vorlagellm/chains.py
vorlagellm/ensemble.py
vorlagellm/languages.py
vorlagellm/llms.py
vorlagellm/main.py
vorlagellm/prompts.py
vorlagellm/rag.py
vorlagellm/tei.py
vorlagellm-0.1.1.dist-info/LICENSE
vorlagellm-0.1.1.dist-info/METADATA
vorlagellm-0.1.1.dist-info/WHEEL
vorlagellm-0.1.1.dist-info/entry_points.txt
vorlagellm-0.1.1.dist-info/RECORD
