Metadata-Version: 2.1
Name: vorlagellm
Version: 0.1.1
Summary: Uses an LLM to determine which were plausible readings in the Vorlage of a translation of a text.
Home-page: https://github.com/rbturnbull/vorlagellm/
License: Apache-2.0
Keywords: llm
Author: Robert Turnbull
Author-email: robert.turnbull@unimelb.edu.au
Requires-Python: >=3.10,<4.0
Classifier: Intended Audience :: Science/Research
Classifier: License :: OSI Approved :: Apache Software License
Classifier: Programming Language :: Python :: 3
Classifier: Programming Language :: Python :: 3.10
Classifier: Programming Language :: Python :: 3.11
Classifier: Programming Language :: Python :: 3.12
Classifier: Topic :: Scientific/Engineering :: Artificial Intelligence
Classifier: Topic :: Software Development :: Libraries :: Python Modules
Requires-Dist: chromadb (>=0.5.0,<0.6.0)
Requires-Dist: docutils (!=0.21.post1)
Requires-Dist: langchain (>=0.1.17)
Requires-Dist: langchain-anthropic (>=0.1.15,<0.2.0)
Requires-Dist: langchain-community (>=0.0.36)
Requires-Dist: langchain-openai (>=0.1.6)
Requires-Dist: lxml (>=5.2.1,<6.0.0)
Requires-Dist: openai (>=1.25.1,<2.0.0)
Requires-Dist: rich (>=13.7.1,<14.0.0)
Requires-Dist: transformers (>=4.43.2,<5.0.0)
Project-URL: Documentation, https://rbturnbull.github.io/vorlagellm
Project-URL: Repository, https://github.com/rbturnbull/vorlagellm/
